{
  "report_date": "2026-05-09",
  "report_time": "2026-05-09 08:30 (台灣時間)",
  "last_update": "2026-05-09 08:30 (台灣時間)",
  "market_sentiment": {
    "vix": {
      "value": 17.19,
      "change": "+0.11",
      "level": "中",
      "note": "VIX 目前 17.19，市場波動中。"
    },
    "dxy": {
      "value": 97.84,
      "direction": "↓",
      "note": "美元指數 97.84，趨勢走弱。"
    },
    "oil_brent": {
      "value": 100.49,
      "direction": "↑",
      "note": "布蘭特原油 100.49 美元，趨勢上漲。"
    },
    "today_focus": [
      "歐洲央行執委施納貝爾發表談話",
      "美聯準官員古爾斯比、沃勒、鮑曼等多位官員發表談話",
      "美伊地緣政治局勢最新進展及對油價影響"
    ]
  },
  "futures_data": {
    "YM1": {
      "name": "E-迷你道瓊指數",
      "current_price": 49691.0,
      "previous_close": 49700.0,
      "currency": "USD",
      "change_points": -9.0,
      "change_percent": -0.02,
      "volume": "111557",
      "support": 49340.0,
      "resistance": 50030.0,
      "support_basis": "以 MA20 均線位置作為支撐參考",
      "resistance_basis": "以前波高點 50034 附近作為壓力參考",
      "timestamp": "2026-05-09 06:05 (台灣時間)"
    },
    "NQ1": {
      "name": "E-迷你那斯達克指數",
      "current_price": 29332.5,
      "previous_close": 28682.25,
      "currency": "USD",
      "change_points": 650.25,
      "change_percent": 2.27,
      "volume": "637911",
      "support": 28700.0,
      "resistance": 29500.0,
      "support_basis": "以 5/6 收盤價及 MA5 均線作為支撐",
      "resistance_basis": "以整數關卡及布林上軌附近作為壓力",
      "timestamp": "2026-05-09 06:05 (台灣時間)"
    },
    "TXF1": {
      "name": "台灣加權指數期貨",
      "current_price": 42292.0,
      "previous_close": 41937.0,
      "currency": "TWD",
      "change_points": 355.0,
      "change_percent": 0.85,
      "volume": "41908",
      "support": 41900.0,
      "resistance": 42500.0,
      "support_basis": "以昨日收盤價及 MA5 均線作為支撐參考",
      "resistance_basis": "以整數關卡及布林上軌 42160 突破後之延伸壓力",
      "timestamp": "2026-05-09 06:05 (台灣時間)"
    }
  },
  "yesterday_analysis": {
    "title": "昨日走勢分析",
    "events": [
      {
        "title": "非農數據超預期與薪資通膨憂慮",
        "description": "美國 4 月非農就業增加 11.5 萬人優於預期，但平均時薪年增 3.6% 引發市場對通膨黏性的擔憂，導致美債收益率反彈，美股高檔震盪。"
      },
      {
        "title": "地緣政治與關稅政策不確定性",
        "description": "美伊緊張局勢升溫及美貿易法院裁定川普全球關稅違法，增加了市場的避險情緒與政策風險溢價。"
      }
    ],
    "economic_data": [
      {
        "indicator": "美國 4 月非農就業人數",
        "actual": "11.5萬",
        "forecast": "6.5萬",
        "previous": "18.5萬 (上修)",
        "impact": "正面",
        "note": "就業增長優於預期，顯示勞動力市場具韌性。"
      },
      {
        "indicator": "美國 4 月失業率",
        "actual": "4.3%",
        "forecast": "4.3%",
        "previous": "4.3%",
        "impact": "中性",
        "note": "失業率維持穩定，符合市場預期。"
      },
      {
        "indicator": "美國 4 月平均時薪 (YoY)",
        "actual": "3.6%",
        "forecast": "3.5%",
        "previous": "3.4% (下修)",
        "impact": "負面",
        "note": "薪資增速略高於預期，引發通膨擔憂。"
      }
    ]
  },
  "futures_analysis": {
    "YM1": {
      "name": "小道瓊",
      "points": [
        {
          "title": "基本面驅動因素",
          "detail": "非農就業數據優於預期雖顯示經濟強韌，但薪資增速上升引發通膨擔憂，加上美貿易法院裁定關稅違法增加政策不確定性，壓抑道指表現。"
        },
        {
          "title": "技術面分析",
          "detail": "目前價格 49691.0 位於 MA5 (49583.8) 與 MA20 (49341.8) 之上，但 MACD 柱狀體為負值 (-14.19)，顯示短期動能轉弱。RSI 為 58.7，處於中性偏強區間。"
        }
      ]
    },
    "NQ1": {
      "name": "小那指",
      "points": [
        {
          "title": "基本面驅動因素",
          "detail": "科技股在非農數據公布前出現獲利回吐，儘管就業數據穩健，但美債收益率因薪資增速超預期而反彈，對高估值科技股形成壓力。"
        },
        {
          "title": "技術面分析",
          "detail": "價格 29332.5 遠高於 MA20 (27303.19)，RSI 高達 82.96 進入超買區。MACD 柱狀體正值擴大 (146.95)，顯示多頭動能強勁但需防範回檔。"
        }
      ]
    },
    "TXF1": {
      "name": "台指期",
      "points": [
        {
          "title": "基本面驅動因素",
          "detail": "受美股高檔震盪及台積電等權值股表現影響，台指期呈現跟隨美股波動態勢。地緣政治風險與美元指數走勢仍是外資動向的關鍵。"
        },
        {
          "title": "技術面分析",
          "detail": "價格 42292.0 站穩 MA5 (40694.74)，RSI 為 79.94 接近超買。MACD 柱狀體維持正值 (277.48)，布林通道上軌 (42160.4) 形成短期壓力。"
        }
      ]
    }
  },
  "today_probability": {
    "title": "今日走勢機率評估",
    "summary": "市場處於高檔震盪格局，非農數據後的通膨預期與地緣政治風險交織，短期多頭動能面臨考驗。",
    "YM1": {
      "up_probability": "45%",
      "down_probability": "55%",
      "analysis": "RSI 為 58.7 處於中性，但 MACD 柱狀體轉負 (-14.19) 顯示動能轉弱，且價格受阻於 50000 關卡。",
      "key_level": "49340 (MA20 支撐位)"
    },
    "NQ1": {
      "up_probability": "50%",
      "down_probability": "50%",
      "analysis": "RSI 高達 82.96 顯示嚴重超買，雖然 MACD 仍強勁，但需防範技術性回檔修正。",
      "key_level": "29140 (布林上軌支撐轉折)"
    },
    "TXF1": {
      "up_probability": "55%",
      "down_probability": "45%",
      "analysis": "RSI 為 79.94 偏強，且 MACD 柱狀體正值擴大 (277.48)，台指期表現相對美股抗跌。",
      "key_level": "41937 (昨日收盤價支撐)"
    }
  },
  "operation_level": {
    "rating": "中等風險",
    "position_size": "減半倉位",
    "reason": "非農數據後市場對通膨預期分歧，且地緣政治風險未除，高檔震盪加劇，建議縮減部位以避險。"
  },
  "investment_advice": {
    "short_term_strategy": [
      "小道瓊若跌破 49340 可嘗試輕倉放空，目標 49000。",
      "小那指在 29500 附近遇阻可考慮獲利了結部分多單。",
      "台指期回測 41900 不破可短線偏多操作。",
      "嚴格執行停損，單筆損失控制在總資金 2% 以內。"
    ],
    "trading_opportunities": [
      "小道瓊進場價 49700，出場價 50100，停損 49400。",
      "小那指進場價 29300，出場價 29600，停損 29100。",
      "台指期進場價 42200，出場價 42600，停損 41900。",
      "利用 VIX 飆升時的恐慌情緒進行逆向短線交易。"
    ],
    "risk_avoidance": [
      "避開在重要官員談話期間進行大額下單。",
      "注意美元指數 DXY 強勢反彈對新興市場貨幣及台指期的壓力。",
      "防範地緣政治突發事件導致的跳空風險。",
      "避免在高 RSI 超買區過度追價。"
    ],
    "position_allocation": [
      "波段多單配置 30%",
      "短線價差交易 20%",
      "避險部位 (如反向 ETF 或選擇權) 10%",
      "現金水位保持 40% 以應對波動。"
    ]
  },
  "conclusion": {
    "summary": "全球市場在強勁就業與通膨憂慮間拉鋸，短期建議保守應對高檔波動。",
    "points": [
      {
        "title": "就業市場韌性與通膨風險並存",
        "detail": "非農數據顯示經濟無虞，但薪資增長超預期使得 Fed 降息預期再度延後，限制指數上行空間。"
      },
      {
        "title": "技術面超買需防範修正",
        "detail": "那指與台指期 RSI 均進入高位，技術面有修正需求，支撐位觀察 MA5 與 MA20。"
      }
    ],
    "advice": "目前市場情緒不穩，操作上應以短線為主，並隨時關注地緣政治與官員談話對市場的衝擊。"
  },
  "news": [
    {
      "title": "美貿易法院裁定川普 10% 全球關稅「違法」",
      "description": "法院認定白宮援引法律依據不適用目前貿易逆差情況，對川普政府關稅政策造成打擊。",
      "impact": "中",
      "timestamp": "2026-05-08 (台灣時間)"
    },
    {
      "title": "美伊局勢持續緊張，川普警告若不簽協議將發動更猛烈打擊",
      "description": "中東地緣政治風險仍高，市場避險情緒與風險偏好交織，油價波動劇烈。",
      "impact": "高",
      "timestamp": "2026-05-08 (台灣時間)"
    },
    {
      "title": "美股周四收跌，道指跌逾 300 點，納指創高後走低",
      "description": "非農數據公布前市場情緒謹慎，獲利了結壓力增加，美股呈現高檔震盪。",
      "impact": "中",
      "timestamp": "2026-05-08 (台灣時間)"
    },
    {
      "title": "Barings BDC 第一季業績喜憂參半，非應計貸款上升",
      "description": "反映信貸壓力增加，市場對企業獲利前景及信貸環境感到擔憂。",
      "impact": "低",
      "timestamp": "2026-05-08 (台灣時間)"
    },
    {
      "title": "鮑爾 Fed 主席任期「最後之舞」，市場聚焦未來政策轉向",
      "description": "鮑爾任期即將結束，市場關注其最後幾次會議對通膨與利率的定調。",
      "impact": "高",
      "timestamp": "2026-05-08 (台灣時間)"
    }
  ],
  "risk_warning": {
    "title": "風險提示",
    "items": [
      {
        "title": "通膨預期再度升溫",
        "detail": "若後續數據顯示通膨難以下降，Fed 可能維持高利率更久。",
        "impact_if_triggered": "美債收益率飆升，科技股 (NQ1) 將面臨劇烈回檔壓力。"
      },
      {
        "title": "中東衝突全面升級",
        "detail": "美伊若發生直接軍事衝突，將導致荷姆茲海峽封鎖。",
        "impact_if_triggered": "油價飆漲，VIX 噴發，全球股市將出現恐慌性拋售。"
      },
      {
        "title": "全球貿易戰重啟",
        "detail": "川普政府若強行推動關稅政策，將引發各國報復。",
        "impact_if_triggered": "全球供應鏈受阻，跨國企業獲利受損，道指 (YM1) 表現將受壓。"
      }
    ]
  }
}